sociallink/README.MD
sociallink/__init__.py
sociallink/requirements.txt
sociallink/thirdparty.json
sociallink-0.10.dist-info/LICENSE.rst
sociallink-0.10.dist-info/METADATA
sociallink-0.10.dist-info/WHEEL
sociallink-0.10.dist-info/top_level.txt
sociallink-0.10.dist-info/RECORD
