Metadata-Version: 2.1
Name: sociallink
Version: 0.10
Summary: Encodes and decodes a URL using a specified symbol to prevent spam detection on platforms like Facebook and YouTube
Home-page: https://github.com/hansalemaos/sociallink
Author: Johannes Fischer
Author-email: aulasparticularesdealemaosp@gmail.com
License: MIT
Keywords: social,link,youtube
Classifier: Development Status :: 4 - Beta
Classifier: Programming Language :: Python :: 3 :: Only
Classifier: Programming Language :: Python :: 3.10
Classifier: Topic :: Software Development :: Libraries :: Python Modules
Classifier: Topic :: Utilities
License-File: LICENSE.rst
